MANIFEST.in
README.txt
setup.py
Products/__init__.py
Products.PloneboardModerationWorkflow.egg-info/PKG-INFO
Products.PloneboardModerationWorkflow.egg-info/SOURCES.txt
Products.PloneboardModerationWorkflow.egg-info/dependency_links.txt
Products.PloneboardModerationWorkflow.egg-info/entry_points.txt
Products.PloneboardModerationWorkflow.egg-info/namespace_packages.txt
Products.PloneboardModerationWorkflow.egg-info/not-zip-safe
Products.PloneboardModerationWorkflow.egg-info/requires.txt
Products.PloneboardModerationWorkflow.egg-info/top_level.txt
Products/PloneboardModerationWorkflow/__init__.py
Products/PloneboardModerationWorkflow/config.py
Products/PloneboardModerationWorkflow/configure.zcml
Products/PloneboardModerationWorkflow/localroles.py
Products/PloneboardModerationWorkflow/tests.py
Products/PloneboardModerationWorkflow/profiles/default/metadata.xml
Products/PloneboardModerationWorkflow/profiles/default/rolemap.xml
Products/PloneboardModerationWorkflow/profiles/default/workflows.xml
Products/PloneboardModerationWorkflow/profiles/default/workflows/ploneboard_comment_workflow/definition.xml
Products/PloneboardModerationWorkflow/profiles/default/workflows/ploneboard_conversation_workflow/definition.xml
Products/PloneboardModerationWorkflow/profiles/default/workflows/ploneboard_editable_comment_workflow/definition.xml
Products/PloneboardModerationWorkflow/profiles/default/workflows/ploneboard_forum_workflow/definition.xml
Products/PloneboardModerationWorkflow/profiles/default/workflows/ploneboard_workflow/definition.xml
docs/HISTORY.txt
docs/INSTALL.txt
docs/LICENSE.GPL
docs/LICENSE.txt