Metadata-Version: 1.1
Name: Products.PloneboardModerationWorkflow
Version: 0.1.4
Summary: An alternative workflow (and optional Moderator role) for Ploneboard product
Home-page: http://svn.plone.org/svn/collective/Products.PloneboardModerationWorkflow/
Author: RedTurtle Technology
Author-email: sviluppoplone@redturtle.net
License: GPL
Keywords: plone ploneboard workflow moderation
Platform: UNKNOWN
Classifier: Framework :: Plone
Classifier: Programming Language :: Python
